{
  "version": "0.2",
  "language": "en,ru",
  "import": ["@cspell/dict-ru/cspell-ext.json"],
  "languageSettings": [
    {
      "languageId": "markdown",
      "locale": "en,ru",
      "dictionaries": ["en", "ru"]
    },
    {
      "languageId": "typescript",
      "locale": "en"
    },
    {
      "languageId": "javascript",
      "locale": "en"
    }
  ],
  "dictionaries": ["en", "ru"],
  "words": [
    "ФАЗА",
    "ИНФРАСТРУКТУРА",
    "БАЗОВОЕ",
    "ОКРУЖЕНИЕ",
    "ЗАДАЧИ",
    "Блок",
    "Настройка",
    "монорепо",
    "Статус",
    "ПОЛНОСТЬЮ",
    "ЗАВЕРШЕН",
    "Реализовано",
    "Монорепо",
    "структура",
    "полной",
    "архитектурой",
    "модулями",
    "современным",
    "Supabase",
    "интеграция",
    "миграциями",
    "настройки",
    "конфигурируемыми",
    "документацией",
    "Локальная",
    "связка",
    "Базовые",
    "эндпоинты",
    "аннотациями",
    "система",
    "конфигурация",
    "строгими",
    "правилами",
    "контейнеризация",
    "Зависимости",
    "обновлены",
    "последних",
    "версий",
    "выполнения",
    "Создана",
    "Настроен",
    "Подключен",
    "Настроена",
    "Созданы",
    "базовые",
    "Обновлены",
    "зависимости",
    "проверки",
    "сборка",
    "проходят",
    "успешно",
    "ГОТОВО",
    "Система",
    "ролей",
    "безопасности",
    "уровнями",
    "доступа",
    "разрешений",
    "детальными",
    "правами",
    "категориям",
    "аутентификации",
    "маппинга"
  ],
  "ignorePaths": [
    "node_modules/**",
    "dist/**",
    "build/**",
    "coverage/**",
    "*.min.js",
    "*.min.css",
    "pg_data/**",
    "backups/**"
  ],
  "files": ["**/*.md", "**/*.ts", "**/*.tsx", "**/*.js", "**/*.jsx"]
}
